[
 {
  "id": 1,
  "email": "guillermosebastianbarra@gmail.com",
  "nombre": " guille",
  "password": [
   "123",
   "1123"
  ],
  "pais": "Argentina"
 },
 {
  "id": 2,
  "email": "lucia@dh.com",
  "nombre": "lucia",
  "password": [
   "abc",
   "abc"
  ],
  "pais": "Uruguay"
 },
 {
  "id": 3,
  "email": "nico@dh.com",
  "nombre": "nico",
  "password": [
   "ooo",
   "ooo"
  ],
  "pais": "Uruguay"
 },
 {
  "id": 4,
  "email": "jose@dh.com",
  "nombre": "pepe",
  "password": [
   "kkk",
   "kkk"
  ],
  "pais": "Argentina"
 },
 {
  "id": 5,
  "email": "jia@h.com",
  "nombre": "jia",
  "password": [
   "123",
   "123"
  ],
  "pais": "Chile"
 },
 {
  "id": 6,
  "email": "jose@d.com",
  "nombre": "uu",
  "password": [
   "uu",
   "uu"
  ],
  "pais": "Argentina"
 },
 {
  "id": 7,
  "email": "guillermosebastianbarra@gmil.com",
  "nombre": " guille",
  "password": "wwwww",
  "pais": "Argentina"
 },
 {
  "id": 8,
  "email": "guillermosebastianbarra@gil.com",
  "nombre": " guille",
  "password": "$2a$10$s/xbNCL2BGEeMn3UR8i1IuhABRaFWEeSMV6jTSboDy1rAgXfLfz4.",
  "pais": "Argentina"
 },
 {
  "id": 9,
  "email": "guillermosebastianbarra@mail.com",
  "nombre": " guille",
  "password": "$2a$10$ycWViiiYNSs84x0.nfDo.OA5xj.EKvb8ByKxS4OmxYL0rSeCAXfU6",
  "pais": "Argentina"
 },
 {
  "id": 10,
  "email": "joe@hf.com",
  "nombre": "joe",
  "password": "$2a$10$JgY3y9kWoOb9f.14GW5vdOlyFNkWDtReVspWb3ExK2VhhFzbuiwk.",
  "pais": "Argentina"
 },
 {
  "id": 11,
  "email": "maria@hf.com",
  "nombre": "mari",
  "password": "$2a$10$qG2StWVL2ZmLuNUUESUGce0jRsjPH7DlXgRFkU1Xr1PUEaVmlEdGS",
  "pais": "Argentina"
 },
 {
  "id": 12,
  "email": "guillermosebastianbarra@gm.com",
  "nombre": "diego",
  "password": "$2a$10$SDiyY.RYLQoryV6/ZsxNpe090Wjncg0uaAKyK.rHcUiyyArvyVyWK",
  "pais": "Argentina"
 },
 {
  "id": 13,
  "email": "nmgomezok@gmail.com",
  "nombre": "Nicolas Gomez",
  "password": "$2a$10$hg6JKhSYxXT1BmJspl5Ju.E5NGg93vbJpHteeIUnHEUrLPjpmOuyy",
  "pais": "Argentina"
 },
 {
  "id": 14,
  "email": "coco@coco.com",
  "nombre": "coco",
  "password": "$2a$10$PYlUyOJmqOlVtyG9k5oByudh2np7QNvP8cG.p7bix/XNcRnHKTGkm",
  "pais": "Argentina"
 },
 {
  "id": 15,
  "email": "pedro@pedro.com",
  "nombre": "Pedro Juan",
  "password": "$2a$10$SHT/EHPr7lJOQEshNAI1Seq.enKwarauDxkWxzhK1HfXuLet8SEfO",
  "pais": "Chile"
 },
 {
  "id": 16,
  "email": "hola@hola.com",
  "nombre": "Nicolas",
  "password": "$2a$10$hZ9f88H/HFEuFud1fupamuDeBaYWHNg8foW4hPuuGL/0KSv7obtqC",
  "pais": "Chile"
 },
 {
  "id": 17,
  "email": "natalia@natalia.com",
  "nombre": "natalia",
  "password": "$2a$10$OsLqxvVmOIWI6NzYaEwqPuovFkyeRURYjtkLmJiRgbRYRBJHVJBJO",
  "pais": "Chile"
 }
]